[
    {
        "id":  "6a22f11d0010648f7f88",
        "genre":  "Voice of People",
        "locationDistrict":  "Darjeeling",
        "locationArea":  "Main bajar"
    },
    {
        "id":  "6a22f1fc003822b3bdfb",
        "genre":  "Voice of People",
        "locationDistrict":  "Darjeeling",
        "locationArea":  "Main bajar"
    },
    {
        "id":  "6a22f297003401239f84",
        "genre":  "Voice of People",
        "locationDistrict":  "Kalimpong",
        "locationArea":  "Kalimpong"
    },
    {
        "id":  "6a22f31100073dfb1d7e",
        "genre":  "Voice of People",
        "locationDistrict":  "Kurseong",
        "locationArea":  "Kurseong"
    },
    {
        "id":  "6a23d1c20029cad2ae52",
        "genre":  "Voice of People",
        "locationDistrict":  "Darjeeling",
        "locationArea":  "Youtube"
    },
    {
        "id":  "6a23d40c001426ec235f",
        "genre":  "Voice of People",
        "locationDistrict":  "Darjeeling",
        "locationArea":  "Youtube"
    },
    {
        "id":  "6a23d69400257de3b27d",
        "genre":  "Voice of People",
        "locationDistrict":  "Darjeeling",
        "locationArea":  "Delhi"
    },
    {
        "id":  "6a26aaef30f3603ddffa",
        "genre":  "Sports",
        "locationDistrict":  "Darjeeling",
        "locationArea":  "Darjeeling"
    },
    {
        "id":  "6a270c9cde99499e5bd3",
        "genre":  "Politics",
        "locationDistrict":  "Darjeeling",
        "locationArea":  "Darjeeling"
    },
    {
        "id":  "6a270ecbce49d75a9d10",
        "genre":  "Voice of People",
        "locationDistrict":  "West Bengal",
        "locationArea":  "Darjeeling"
    },
    {
        "id":  "6a27bcb28d1a509bd83b",
        "genre":  "Voice of People",
        "locationDistrict":  "Darjeeling",
        "locationArea":  "darjeeling bazar"
    },
    {
        "id":  "6a27c648e4db109f38cf",
        "genre":  "Voice of People",
        "locationDistrict":  "Darjeeling",
        "locationArea":  "Tukvar Valley , Darjeeling"
    },
    {
        "id":  "6a29680b9b0f9d9238b7",
        "genre":  "Voice of People",
        "locationDistrict":  "Siliguri",
        "locationArea":  "Silliguri"
    },
    {
        "id":  "6a2a175175f859f26edd",
        "genre":  "Voice of People",
        "locationDistrict":  "Darjeeling",
        "locationArea":  "Darjeeling"
    },
    {
        "id":  "6a2a6bdbdc6bcd10d8e0",
        "genre":  "Voice of People",
        "locationDistrict":  "Darjeeling",
        "locationArea":  "Darjeeling"
    },
    {
        "id":  "6a2a6ed5de9b3a772a07",
        "genre":  "Voice of People",
        "locationDistrict":  "Darjeeling",
        "locationArea":  "Darjeeling"
    },
    {
        "id":  "6a2aca15f0ee1885e840",
        "genre":  "Voice of People",
        "locationDistrict":  "Darjeeling",
        "locationArea":  "darjeeling bazar"
    },
    {
        "id":  "6a2b06b0bbf71a35f848",
        "genre":  "Voice of People",
        "locationDistrict":  "Darjeeling",
        "locationArea":  "Lepcha busty"
    },
    {
        "id":  "6a2b1f03acead131fc9f",
        "genre":  "Voice of People",
        "locationDistrict":  "Darjeeling",
        "locationArea":  "Darjeeling"
    },
    {
        "id":  "6a2bcf1a3a7494dc6138",
        "genre":  "Politics",
        "locationDistrict":  "Darjeeling",
        "locationArea":  "kolkota"
    },
    {
        "id":  "6a2c146fc70dcf575e53",
        "genre":  "Sports",
        "locationDistrict":  "Darjeeling",
        "locationArea":  "Chaurasta,Darjeeling"
    },
    {
        "id":  "6a2c227498145f1c3242",
        "genre":  "Culture",
        "locationDistrict":  "Darjeeling",
        "locationArea":  "Darjeeling"
    },
    {
        "id":  "6a2c2febe1e11c70ff5e",
        "genre":  "Sports",
        "locationDistrict":  "Darjeeling",
        "locationArea":  "Sukepokhari"
    },
    {
        "id":  "6a2ce924d52094d32ba5",
        "genre":  "Politics",
        "locationDistrict":  "Darjeeling",
        "locationArea":  "Sukhia pokhari"
    },
    {
        "id":  "6a2d48640b0a7b689b6e",
        "genre":  "Voice of People",
        "locationDistrict":  "Kurseong",
        "locationArea":  "kurseong"
    },
    {
        "id":  "6a2d513b76f97cee4ef1",
        "genre":  "Health",
        "locationDistrict":  "Darjeeling",
        "locationArea":  "Darjeeling"
    },
    {
        "id":  "6a2d780a753d3146f788",
        "genre":  "Voice of People",
        "locationDistrict":  "Darjeeling",
        "locationArea":  "darjeeling bazar"
    },
    {
        "id":  "6a2d79dc976b613806d2",
        "genre":  "Voice of People",
        "locationDistrict":  "Darjeeling",
        "locationArea":  "darjeeling bazar"
    },
    {
        "id":  "6a2e62104a480c4e20d4",
        "genre":  "Voice of People",
        "locationDistrict":  "Darjeeling",
        "locationArea":  "Lebong valley"
    },
    {
        "id":  "6a2e6ccc6e0716ac79b9",
        "genre":  "Sports",
        "locationDistrict":  "Darjeeling",
        "locationArea":  "Darjeeling"
    },
    {
        "id":  "6a2ec240187dced05a35",
        "genre":  "Voice of People",
        "locationDistrict":  "Mirik",
        "locationArea":  "Dudhia"
    },
    {
        "id":  "6a2ec2eda9f2c2ce3652",
        "genre":  "Voice of People",
        "locationDistrict":  "Darjeeling",
        "locationArea":  "Darjeeling railway station"
    },
    {
        "id":  "6a301d3cbc8fc706e435",
        "genre":  "Voice of People",
        "locationDistrict":  "Kurseong",
        "locationArea":  "Kurseong"
    },
    {
        "id":  "6a301de4980704c273d5",
        "genre":  "Voice of People",
        "locationDistrict":  "Mirik",
        "locationArea":  "Dudhia bridge"
    },
    {
        "id":  "6a30ea05dd97910c2f96",
        "genre":  "Politics",
        "locationDistrict":  "Darjeeling",
        "locationArea":  "Darjeeling"
    },
    {
        "id":  "6a30ea9facca4af85bc8",
        "genre":  "Politics",
        "locationDistrict":  "Darjeeling",
        "locationArea":  "darjeeling bazar"
    },
    {
        "id":  "6a30f15db3c06009fbcc",
        "genre":  "Voice of People",
        "locationDistrict":  "Darjeeling",
        "locationArea":  "Darjeeling"
    },
    {
        "id":  "6a30f3b5e1aac480c2e8",
        "genre":  "Voice of People",
        "locationDistrict":  "Darjeeling",
        "locationArea":  "Darjeeling"
    },
    {
        "id":  "6a3113a012235613fd75",
        "genre":  "Voice of People",
        "locationDistrict":  "Siliguri",
        "locationArea":  "Darjeeling"
    },
    {
        "id":  "6a311aabca4fa6c98a2f",
        "genre":  "Voice of People",
        "locationDistrict":  "Siliguri",
        "locationArea":  "Darjeeling"
    },
    {
        "id":  "6a311e9254a1fbfac6cd",
        "genre":  "Voice of People",
        "locationDistrict":  "Darjeeling",
        "locationArea":  "Darjeeling"
    },
    {
        "id":  "6a315e7846b76b8e1cfe",
        "genre":  "Voice of People",
        "locationDistrict":  "Darjeeling",
        "locationArea":  "Darjeeling"
    },
    {
        "id":  "6a3177ba70a42cdcb676",
        "genre":  "Voice of People",
        "locationDistrict":  "Kurseong",
        "locationArea":  "Kurseong"
    },
    {
        "id":  "6a3254bcc8ea7b757a68",
        "genre":  "Voice of People",
        "locationDistrict":  "Kurseong",
        "locationArea":  "Kurseong"
    },
    {
        "id":  "6a329599ac412466805d",
        "genre":  "Voice of People",
        "locationDistrict":  "Kurseong",
        "locationArea":  "kurseong"
    },
    {
        "id":  "6a329702a8f317c52702",
        "genre":  "Voice of People",
        "locationDistrict":  "Darjeeling",
        "locationArea":  "Darjeeling"
    },
    {
        "id":  "6a33f203c184ac313e69",
        "genre":  "Voice of People",
        "locationDistrict":  "Darjeeling",
        "locationArea":  "Darjeeling"
    },
    {
        "id":  "6a342e5fbb848d6795ed",
        "genre":  "Voice of People",
        "locationDistrict":  "Darjeeling",
        "locationArea":  "Darjeeling"
    },
    {
        "id":  "6a34ce0587a5c8bbf570",
        "genre":  "Voice of People",
        "locationDistrict":  "Darjeeling",
        "locationArea":  "Darjeeling main market"
    },
    {
        "id":  "6a34f4f9b67063a7b511",
        "genre":  "Politics",
        "locationDistrict":  "Darjeeling",
        "locationArea":  "Darjeeling"
    },
    {
        "id":  "6a34f6f92749b4deb17a",
        "genre":  "Voice of People",
        "locationDistrict":  "Kurseong",
        "locationArea":  "Darjeeling"
    },
    {
        "id":  "6a34f88282fd7445b47a",
        "genre":  "Voice of People",
        "locationDistrict":  "Kurseong",
        "locationArea":  "Darjeeling"
    },
    {
        "id":  "6a35a0bb3d12103adf53",
        "genre":  "Voice of People",
        "locationDistrict":  "Darjeeling",
        "locationArea":  "Darjeeling district"
    },
    {
        "id":  "6a35a19ba4de11a529b6",
        "genre":  "Voice of People",
        "locationDistrict":  "Kurseong",
        "locationArea":  "Kurseong"
    },
    {
        "id":  "6a36475b53e482c80bdb",
        "genre":  "Voice of People",
        "locationDistrict":  "Darjeeling",
        "locationArea":  "Darjeeling bazar"
    },
    {
        "id":  "6a37800a4b0045d7515c",
        "genre":  "Education",
        "locationDistrict":  "Darjeeling",
        "locationArea":  "Darjeeling"
    },
    {
        "id":  "6a3a35d1571c4b2f7888",
        "genre":  "Voice of People",
        "locationDistrict":  "West Bengal",
        "locationArea":  "Kolkotta"
    },
    {
        "id":  "6a3a9bbb559dd0de7ff5",
        "genre":  "Voice of People",
        "locationDistrict":  "Siliguri",
        "locationArea":  "Darjeeling"
    },
    {
        "id":  "6a3ac9a1197758bb4778",
        "genre":  "Voice of People",
        "locationDistrict":  "Darjeeling",
        "locationArea":  "Darjeeling"
    },
    {
        "id":  "6a3ac9f22e0eb5893b1c",
        "genre":  "Politics",
        "locationDistrict":  "Darjeeling",
        "locationArea":  "Darjeeling"
    },
    {
        "id":  "6a3aca454bb00aeead8c",
        "genre":  "Politics",
        "locationDistrict":  "Darjeeling",
        "locationArea":  "Darjeeling"
    },
    {
        "id":  "6a3acb4102ce3ba728cd",
        "genre":  "Politics",
        "locationDistrict":  "Darjeeling",
        "locationArea":  "Darjeeling"
    },
    {
        "id":  "6a3acc14c566c1cb0194",
        "genre":  "Voice of People",
        "locationDistrict":  "Darjeeling",
        "locationArea":  "Darjeeling"
    },
    {
        "id":  "6a3bd5b1f2d598540c0b",
        "genre":  "Voice of People",
        "locationDistrict":  "Kurseong",
        "locationArea":  "Kurseong"
    },
    {
        "id":  "6a3c2aa6e75e4b4df9eb",
        "genre":  "Politics",
        "locationDistrict":  "Darjeeling",
        "locationArea":  "Kurseong"
    },
    {
        "id":  "6a3cc7f4b30f543db8cb",
        "genre":  "Voice of People",
        "locationDistrict":  "Siliguri",
        "locationArea":  "NH 10"
    },
    {
        "id":  "6a3cce0abf8fd85a7f09",
        "genre":  "Voice of People",
        "locationDistrict":  "Darjeeling",
        "locationArea":  "Darjeeling"
    },
    {
        "id":  "6a3cf2fd904dcb8ddfb0",
        "genre":  "Health",
        "locationDistrict":  "Darjeeling",
        "locationArea":  "mungpoo"
    },
    {
        "id":  "6a3d1f73c36dd4ae6cfe",
        "genre":  "Politics",
        "locationDistrict":  "Darjeeling",
        "locationArea":  "Darjeeling"
    },
    {
        "id":  "6a3d6828cc60f950fee2",
        "genre":  "Voice of People",
        "locationDistrict":  "Kalimpong",
        "locationArea":  "Darjeeling"
    },
    {
        "id":  "6a3e2bfedea105c79812",
        "genre":  "Voice of People",
        "locationDistrict":  "Darjeeling",
        "locationArea":  "Darjeeling"
    },
    {
        "id":  "6a3e6d6d3cc0f8062b96",
        "genre":  "Voice of People",
        "locationDistrict":  "Darjeeling",
        "locationArea":  "Siliguri"
    },
    {
        "id":  "6a3efddbd9cebee6a2e2",
        "genre":  "Politics",
        "locationDistrict":  "Darjeeling",
        "locationArea":  "Darjeeling"
    },
    {
        "id":  "6a3f6ce57c7b63e0a193",
        "genre":  "Voice of People",
        "locationDistrict":  "Darjeeling",
        "locationArea":  "Darjeeling"
    },
    {
        "id":  "6a3feacbb90f37dfd5ef",
        "genre":  "Voice of People",
        "locationDistrict":  "Darjeeling",
        "locationArea":  "Darjeeling"
    },
    {
        "id":  "6a409c2d025635d6a46a",
        "genre":  "Voice of People",
        "locationDistrict":  "Kalimpong",
        "locationArea":  "Darjeeling"
    },
    {
        "id":  "6a40d5b6750ea0f85417",
        "genre":  "Voice of People",
        "locationDistrict":  "Darjeeling",
        "locationArea":  "Sikkim"
    },
    {
        "id":  "6a40f7f0126f9321e80d",
        "genre":  "Voice of People",
        "locationDistrict":  "Darjeeling",
        "locationArea":  "Darjeeling"
    },
    {
        "id":  "6a423a2017fbda62e25f",
        "genre":  "Voice of People",
        "locationDistrict":  "Darjeeling",
        "locationArea":  "Darjeeling"
    },
    {
        "id":  "6a4290f6a2c6b3e53529",
        "genre":  "Tourism",
        "locationDistrict":  "Darjeeling",
        "locationArea":  "Sandakphu"
    },
    {
        "id":  "6a4378f56f6889ef2e12",
        "genre":  "Tourism",
        "locationDistrict":  "Darjeeling",
        "locationArea":  "Darjeeling"
    },
    {
        "id":  "6a4381005a13876a84ce",
        "genre":  "Voice of People",
        "locationDistrict":  "Darjeeling",
        "locationArea":  "Darjeeling"
    },
    {
        "id":  "6a44d0c04d2959f177d0",
        "genre":  "Sports",
        "locationDistrict":  "Darjeeling",
        "locationArea":  "Darjeeling"
    },
    {
        "id":  "6a44fad0598f3f4ddc7b",
        "genre":  "Sports",
        "locationDistrict":  "Darjeeling",
        "locationArea":  "Darjeeling"
    },
    {
        "id":  "6a464d07eb7b3c90b7ce",
        "genre":  "Sports",
        "locationDistrict":  "Darjeeling",
        "locationArea":  "Namdok, Sikkim"
    },
    {
        "id":  "6a4658587fcf3e7c158e",
        "genre":  "Tourism",
        "locationDistrict":  "Darjeeling",
        "locationArea":  "Singmari,Darjeeling"
    },
    {
        "id":  "6a47365b1c031dc19043",
        "genre":  "Voice of People",
        "locationDistrict":  "Darjeeling",
        "locationArea":  "Darjeeling"
    },
    {
        "id":  "6a48087948894b9599aa",
        "genre":  "Voice of People",
        "locationDistrict":  "Darjeeling",
        "locationArea":  "Darjeeling"
    },
    {
        "id":  "6a480c1c28579fd99807",
        "genre":  "Voice of People",
        "locationDistrict":  "Darjeeling",
        "locationArea":  "Darjeeling"
    },
    {
        "id":  "6a492c943d181d21d326",
        "genre":  "Voice of People",
        "locationDistrict":  "Darjeeling",
        "locationArea":  "Sikkim"
    },
    {
        "id":  "6a4a489d40c60d088fcf",
        "genre":  "Sports",
        "locationDistrict":  "Darjeeling",
        "locationArea":  "Jorethang,sikkim"
    },
    {
        "id":  "6a4a655c7a710c9cbdc5",
        "genre":  "Editorial",
        "locationDistrict":  "Darjeeling",
        "locationArea":  "kurseong "
    },
    {
        "id":  "6a4bc5390cbe3cb959d1",
        "genre":  "Culture",
        "locationDistrict":  "Darjeeling",
        "locationArea":  "Darjeeling"
    },
    {
        "id":  "6a4cd00739744b810132",
        "genre":  "Politics",
        "locationDistrict":  "Darjeeling",
        "locationArea":  "Darjeeling"
    },
    {
        "id":  "6a4cd4d9be387c8c198d",
        "genre":  "Voice of People",
        "locationDistrict":  "Darjeeling",
        "locationArea":  "Darjeeling"
    },
    {
        "id":  "6a4cdac3a5bfb7be0dfa",
        "genre":  "Voice of People",
        "locationDistrict":  "Darjeeling",
        "locationArea":  "Darjeeling"
    },
    {
        "id":  "6a4e45ce47416f2ba44c",
        "genre":  "Sports",
        "locationDistrict":  "Darjeeling",
        "locationArea":  "Atlanta,"
    },
    {
        "id":  "6a4f87383e55657b5c90",
        "genre":  "Voice of People",
        "locationDistrict":  "Kalimpong",
        "locationArea":  "Kalimpong"
    },
    {
        "id":  "6a50b5ea943ffd6ee9c7",
        "genre":  "Voice of People",
        "locationDistrict":  "Mirik",
        "locationArea":  "DARJEELING"
    },
    {
        "id":  "6a50b65bebbe5527ed59",
        "genre":  "Voice of People",
        "locationDistrict":  "Darjeeling",
        "locationArea":  "Darjeeling"
    },
    {
        "id":  "6a50b7e135a2868d093a",
        "genre":  "Politics",
        "locationDistrict":  "Darjeeling",
        "locationArea":  "Darjeeling"
    },
    {
        "id":  "6a50f0a8047fc1d89b09",
        "genre":  "Technology",
        "locationDistrict":  "Darjeeling",
        "locationArea":  "Darjeeling"
    },
    {
        "id":  "6a50f7ab921a546c0584",
        "genre":  "Voice of People",
        "locationDistrict":  "Darjeeling",
        "locationArea":  "Darjeeling"
    },
    {
        "id":  "6a5106a1cff91a4d9450",
        "genre":  "Voice of People",
        "locationDistrict":  "Darjeeling",
        "locationArea":  "Darjeeling"
    },
    {
        "id":  "6a51fcce7946f6b774d8",
        "genre":  "Voice of People",
        "locationDistrict":  "Darjeeling",
        "locationArea":  "Darjeeling"
    },
    {
        "id":  "6a533b6251e42b1324ac",
        "genre":  "Voice of People",
        "locationDistrict":  "Darjeeling",
        "locationArea":  "Darjeeling"
    },
    {
        "id":  "6a55029eb764883e20b0",
        "genre":  "Voice of People",
        "locationDistrict":  "Darjeeling",
        "locationArea":  "Darjeeling"
    },
    {
        "id":  "6a55d00ca5a70f19c991",
        "genre":  "Voice of People",
        "locationDistrict":  "Darjeeling",
        "locationArea":  "Darjeeling"
    },
    {
        "id":  "6a5655f660d39fc1a0d9",
        "genre":  "Voice of People",
        "locationDistrict":  "Darjeeling",
        "locationArea":  "Darjeeling"
    },
    {
        "id":  "6a566853973c10a3152e",
        "genre":  "Voice of People",
        "locationDistrict":  "Darjeeling",
        "locationArea":  "Bijanbari "
    },
    {
        "id":  "6a567ead47051666d4f0",
        "genre":  "Voice of People",
        "locationDistrict":  "West Bengal",
        "locationArea":  "Kalimpong "
    },
    {
        "id":  "6a576f5dc3ef332e2702",
        "genre":  "Culture",
        "locationDistrict":  "Darjeeling",
        "locationArea":  "Darjeeling"
    },
    {
        "id":  "6a5790d27dae3137934b",
        "genre":  "Voice of People",
        "locationDistrict":  "Darjeeling",
        "locationArea":  "Darjeeling"
    },
    {
        "id":  "6a5881a3a2faaf3e3caa",
        "genre":  "Voice of People",
        "locationDistrict":  "Darjeeling",
        "locationArea":  "Darjeeling"
    },
    {
        "id":  "6a58d825369f5774c3a4",
        "genre":  "Voice of People",
        "locationDistrict":  "Kalimpong",
        "locationArea":  "Kalimpong"
    },
    {
        "id":  "6a5919c131ef842302fe",
        "genre":  "Voice of People",
        "locationDistrict":  "Darjeeling",
        "locationArea":  "Darjeeling"
    },
    {
        "id":  "6a5b261d705194523910",
        "genre":  "Voice of People",
        "locationDistrict":  "Darjeeling",
        "locationArea":  "Darjeeling"
    },
    {
        "id":  "6a5bec0e4ca2d74e646e",
        "genre":  "Voice of People",
        "locationDistrict":  "Darjeeling",
        "locationArea":  "Darjeeling"
    },
    {
        "id":  "6a5cf945675f4c30aa2c",
        "genre":  "Voice of People",
        "locationDistrict":  "Darjeeling",
        "locationArea":  "Darjeeling"
    },
    {
        "id":  "6a5da91e73084418563e",
        "genre":  "Editorial",
        "locationDistrict":  "Darjeeling",
        "locationArea":  "Darjeeling"
    },
    {
        "id":  "6a5dfe88c9d13bb8bc6b",
        "genre":  "Voice of People",
        "locationDistrict":  "Darjeeling",
        "locationArea":  "Darjeeling"
    }
]
